raglan-0.0.1a0.dist-info/METADATA
raglan-0.0.1a0.dist-info/WHEEL
raglan/__init__.py
raglan-0.0.1a0.dist-info/RECORD
